rk/__init__.py
rk/bdtreader.py
rk/binning.py
rk/bootstrapping.py
rk/boundaries.py
rk/br_calculator.py
rk/cal_rdf.py
rk/calc_utility.py
rk/calculator.py
rk/ckcov.py
rk/collector.py
rk/const_getter.py
rk/cut_checker.py
rk/cut_getter.py
rk/cutflow.py
rk/cutflow_merger.py
rk/dat_sim_cmp.py
rk/data_filter.py
rk/dbase_paths.py
rk/decay_finder.py
rk/decaymodel_reader.py
rk/descriptors.py
rk/df_getter.py
rk/dfselect.py
rk/differential_efficiency.py
rk/differential_yield.py
rk/dilep_reso.py
rk/ds_getter.py
rk/dummy_reweighter.py
rk/eff_yld_loader.py
rk/efficiency.py
rk/fithst.py
rk/fitwgt.py
rk/gen_stats.py
rk/hist_map.py
rk/inclusive.py
rk/inclusive_decays_weights.py
rk/inclusive_sample_weights.py
rk/jpsi_leakage.py
rk/kcabibbo.py
rk/kinrwt.py
rk/lep_reso.py
rk/make_toy_pid_maps.py
rk/mc_map_calc.py
rk/mcstudy.py
rk/model.py
rk/model_constraints.py
rk/model_uncertainty.py
rk/musg_extractor.py
rk/mv_reweighter.py
rk/mva.py
rk/oscillator.py
rk/particle_dictionary.py
rk/pchain.py
rk/pidreader.py
rk/plot_pulls.py
rk/pr_shapes.py
rk/q2smear.py
rk/reso_extractor.py
rk/sample_tools.py
rk/scale_dcw.py
rk/scales.py
rk/selection.py
rk/set_pdf.py
rk/settings.py
rk/snap_pdf.py
rk/stats.py
rk/swreader.py
rk/swt_copy.py
rk/syst_check.py
rk/trackreader.py
rk/trgreader.py
rk/trig_threshold.py
rk/trigger_swt.py
rk/trigger_tnp.py
rk/truth_eff.py
rk/utilities.py
rk/var_dumper.py
rk/weight_reader.py
rk/wgt_mgr.py
rx_tools-0.2.7.data/scripts/apply_selection
rx_tools-0.2.7.data/scripts/get_trig_binning
rx_tools-0.2.7.data/scripts/job_prc
rx_tools-0.2.7.data/scripts/job_sel
rx_tools-0.2.7.data/scripts/make_evt_dsc
rx_tools-0.2.7.data/scripts/submit_prc
rx_tools-0.2.7.data/scripts/submit_sel
tools_data/inclusive_mc_stats/__init__.py
tools_data/inclusive_mc_stats/bdXcHs.json
tools_data/inclusive_mc_stats/bpXcHs.json
tools_data/inclusive_mc_stats/bsXcHs.json
tools_data/trigger/__init__.py
rx_tools-0.2.7.dist-info/METADATA
rx_tools-0.2.7.dist-info/WHEEL
rx_tools-0.2.7.dist-info/top_level.txt
rx_tools-0.2.7.dist-info/RECORD
