Metadata-Version: 2.1
Name: rx_tools
Version: 0.2.7
Summary: Project containing tools for RX measurement
Requires-Dist: matplotlib
Requires-Dist: pandas
Requires-Dist: rx-scripts >=0.2.2
Requires-Dist: rx-selection >=0.0.4
Requires-Dist: zfit >=0.14.0
Requires-Dist: tqdm
Requires-Dist: numexpr
Requires-Dist: logzero
Requires-Dist: mplhep
